sofascore/__init__.py
sofascore/adapters.py
sofascore-1.2.0.dist-info/LICENSE
sofascore-1.2.0.dist-info/WHEEL
sofascore-1.2.0.dist-info/METADATA
sofascore-1.2.0.dist-info/RECORD
